Metadata-Version: 2.1
Name: secpickle
Version: 0.1.0
Summary: Use Python's Pickle Module Safely
Home-page: https://github.com/firlast/secpickle
Author: Firlast
Author-email: firlastinc@gmail.com
License: UNKNOWN
Keywords: pickle,secure,safely,python
Platform: UNKNOWN
